README.md
setup.py
src/python_cpp_example/__init__.py
src/python_cpp_example/hello.py
src/python_cpp_example.egg-info/PKG-INFO
src/python_cpp_example.egg-info/SOURCES.txt
src/python_cpp_example.egg-info/dependency_links.txt
src/python_cpp_example.egg-info/not-zip-safe
src/python_cpp_example.egg-info/top_level.txt