Metadata-Version: 1.0
Name: python-cpp-example
Version: 0.2
Summary: A hybrid Python/C++ test project
Home-page: UNKNOWN
Author: Benjamin Jack
Author-email: benjamin.r.jack@gmail.com
License: UNKNOWN
Platform: UNKNOWN
